tagliatelle/Client.py
tagliatelle/ClientRequest.py
tagliatelle/LowLevelClient.py
tagliatelle/__init__.py
tagliatelle/data/TagBulkResponse.py
tagliatelle/data/TagRequest.py
tagliatelle/data/TagResponse.py
tagliatelle/data/__init__.py
tagliatelle-0.2.dist-info/METADATA
tagliatelle-0.2.dist-info/WHEEL
tagliatelle-0.2.dist-info/top_level.txt
tagliatelle-0.2.dist-info/RECORD
