Metadata-Version: 2.1
Name: tagliatelle
Version: 0.2
Summary: Client package for Cimpress Tagliatelle
Home-page: http://github.com/Cimpress/cimpress-tagliatelle-python
Author: Rafal Nowosielski
Author-email: rafal@nowosielski.email
License: MIT
Platform: UNKNOWN
